adelphi/__init__.py
adelphi/anonymize.py
adelphi/cql.py
adelphi/exceptions.py
adelphi/export.py
adelphi/gemini.py
adelphi/gh.py
adelphi/nb.py
adelphi/store.py
adelphi-0.2.1.data/scripts/adelphi
adelphi-0.2.1.dist-info/METADATA
adelphi-0.2.1.dist-info/WHEEL
adelphi-0.2.1.dist-info/top_level.txt
adelphi-0.2.1.dist-info/RECORD
