Metadata-Version: 2.1
Name: adelphi
Version: 0.2.1
Summary: Tooling for Adelphi
Home-page: https://github.com/datastax/adelphi
Author: DataStax
License: UNKNOWN
Project-URL: Source, https://github.com/datastax/adelphi
Project-URL: Documentation, https://github.com/datastax/adelphi/blob/master/python/adelphi/README.md
Project-URL: Issues, https://github.com/datastax/adelphi/issues
Platform: UNKNOWN
Classifier: Development Status :: 3 - Alpha
Classifier: Intended Audience :: Developers
Classifier: License :: OSI Approved :: Apache Software License
Classifier: Natural Language :: English
Classifier: Operating System :: OS Independent
Classifier: Programming Language :: Python
Classifier: Programming Language :: Python :: 2.7
Classifier: Programming Language :: Python :: 3.5
Classifier: Programming Language :: Python :: 3.6
Classifier: Programming Language :: Python :: 3.7
Classifier: Programming Language :: Python :: 3.8
Classifier: Programming Language :: Python :: 3.9
Classifier: Programming Language :: Python :: Implementation :: CPython
Classifier: Topic :: Software Development :: Libraries :: Python Modules
Requires-Dist: cassandra-driver (~=3.24)
Requires-Dist: click (~=7.1)
Requires-Dist: PyGithub (~=1.45)
Requires-Dist: PyYAML (~=5.4)
Requires-Dist: backports.tempfile (~=1.0)
